<?xml version="1.0" encoding="UTF-8" ?>
<!-- Copyright (c) 2010-2014 Dassault Systemes, 1993 - 2014 -->
<!DOCTYPE ematrix SYSTEM "ematrixml.dtd">
<ematrix>
  <creationProperties>
    <release>3DEXPERIENCE R2018x HotFix 5(27.2.0.0)</release>
    <datetime>2019-07-11T12:28:44Z</datetime>
    <event>export</event>
    <dtdInfo>&ematrixProductDtd;</dtdInfo>
  </creationProperties>
  <policy id="0.1.9024.29762">
    <adminProperties>
      <name>IMS_DCDecision</name>
      <creationInfo>
        <datetime>2019-07-10T12:06:21Z</datetime>
      </creationInfo>
      <modificationInfo>
        <datetime>2019-07-10T12:06:21Z</datetime>
      </modificationInfo>
      <description>Default Policy for Decision objects</description>
      <propertyList count="10">
        <property>
          <name>MxUpdate Sub Path</name>
          <flags>0</flags>
        </property>
        <property>
          <name>application</name>
          <value>IMS_HNH</value>
          <flags>0</flags>
        </property>
        <property>
          <name>file date</name>
          <value>04-24-2019 14:19:54.000</value>
          <flags>0</flags>
        </property>
        <property>
          <name>installed date</name>
          <value>07-10-2019</value>
          <flags>0</flags>
        </property>
        <property>
          <name>installer</name>
          <value>The MxUpdate Team</value>
          <flags>0</flags>
        </property>
        <property>
          <name>original name</name>
          <value>IMS_DCDecision</value>
          <flags>0</flags>
        </property>
        <property>
          <name>state_Active</name>
          <value>Active</value>
          <flags>0</flags>
        </property>
        <property>
          <name>state_Release</name>
          <value>Release</value>
          <flags>0</flags>
        </property>
        <property>
          <name>state_Superceded</name>
          <value>Superceded</value>
          <flags>0</flags>
        </property>
        <property>
          <name>version</name>
          <value>1</value>
          <flags>0</flags>
        </property>
      </propertyList>
      <historyList count="80">
        <history>
          <datetime>2019-07-10T12:06:21Z</datetime>
          <agent>creator</agent>
          <event>create</event>
          <order>1</order>
          <string>add policy IMS_DCDecision</string>
        </history>
        <history>
          <datetime>2019-07-10T12:06:21Z</datetime>
          <agent>creator</agent>
          <event>modify</event>
          <order>2</order>
          <string>mod policy IMS_DCDecision description 'Default Policy for Decision objects'</string>
        </history>
        <history>
          <datetime>2019-07-10T12:06:21Z</datetime>
          <agent>creator</agent>
          <event>modify</event>
          <order>3</order>
          <string>mod policy IMS_DCDecision add type IMS_DCDecision</string>
        </history>
        <history>
          <datetime>2019-07-10T12:06:21Z</datetime>
          <agent>creator</agent>
          <event>modify</event>
          <order>4</order>
          <string>mod policy IMS_DCDecision sequence 1,2,3,...</string>
        </history>
        <history>
          <datetime>2019-07-10T12:06:21Z</datetime>
          <agent>creator</agent>
          <event>modify</event>
          <order>5</order>
          <string>mod policy IMS_DCDecision add allstate public none none owner none none</string>
        </history>
        <history>
          <datetime>2019-07-10T12:06:21Z</datetime>
          <agent>creator</agent>
          <event>modify</event>
          <order>6</order>
          <string>mod policy IMS_DCDecision allstate revoke public none none filter '' remove revoke public all all revoke owner none none filter '' remove revoke owner all all public none none filter '' remove public all all owner none none filter '' remove owner all all</string>
        </history>
        <history>
          <datetime>2019-07-10T12:06:21Z</datetime>
          <agent>creator</agent>
          <event>modify</event>
          <order>7</order>
          <string>mod policy IMS_DCDecision allstate user 'Global User' key SecuredGlobalUser read read,show,toconnect,todisconnect ancestor organization ancestor project</string>
        </history>
        <history>
          <datetime>2019-07-10T12:06:21Z</datetime>
          <agent>creator</agent>
          <event>modify</event>
          <order>8</order>
          <string>mod policy IMS_DCDecision allstate user IMS_AP_Designer all all</string>
        </history>
        <history>
          <datetime>2019-07-10T12:06:21Z</datetime>
          <agent>creator</agent>
          <event>modify</event>
          <order>9</order>
          <string>mod policy IMS_DCDecision allstate user VPLMLocalCrossOrgContextAccess key ExtendedOwnerReadAccess checkout checkout,read,show,toconnect,todisconnect context owner</string>
        </history>
        <history>
          <datetime>2019-07-10T12:06:21Z</datetime>
          <agent>creator</agent>
          <event>modify</event>
          <order>10</order>
          <string>mod policy IMS_DCDecision allstate login user VPLMAdmin key ExtendedModifyAccessForPLMAdmin changename changename,checkin,modify</string>
        </history>
        <history>
          <datetime>2019-07-10T12:06:21Z</datetime>
          <agent>creator</agent>
          <event>modify</event>
          <order>11</order>
          <string>mod policy IMS_DCDecision allstate login user VPLMAdmin key ExtendedPromoteAccessForPLMAdmin demote demote,promote</string>
        </history>
        <history>
          <datetime>2019-07-10T12:06:21Z</datetime>
          <agent>creator</agent>
          <event>modify</event>
          <order>12</order>
          <string>mod policy IMS_DCDecision allstate login user VPLMAdmin key ExtendedReadAccessForPLMAdmin checkout checkout,read,show,toconnect,todisconnect</string>
        </history>
        <history>
          <datetime>2019-07-10T12:06:21Z</datetime>
          <agent>creator</agent>
          <event>modify</event>
          <order>13</order>
          <string>mod policy IMS_DCDecision add state Active public none none owner none none</string>
        </history>
        <history>
          <datetime>2019-07-10T12:06:21Z</datetime>
          <agent>creator</agent>
          <event>modify</event>
          <order>14</order>
          <string>mod policy IMS_DCDecision add state Superceded public none none owner none none</string>
        </history>
        <history>
          <datetime>2019-07-10T12:06:21Z</datetime>
          <agent>creator</agent>
          <event>modify</event>
          <order>15</order>
          <string>mod policy IMS_DCDecision state Superceded !enforcereserveaccess</string>
        </history>
        <history>
          <datetime>2019-07-10T12:06:21Z</datetime>
          <agent>creator</agent>
          <event>modify</event>
          <order>16</order>
          <string>mod policy IMS_DCDecision state Superceded promote false</string>
        </history>
        <history>
          <datetime>2019-07-10T12:06:21Z</datetime>
          <agent>creator</agent>
          <event>modify</event>
          <order>17</order>
          <string>mod policy IMS_DCDecision state Superceded checkoutHistory false</string>
        </history>
        <history>
          <datetime>2019-07-10T12:06:21Z</datetime>
          <agent>creator</agent>
          <event>modify</event>
          <order>18</order>
          <string>mod policy IMS_DCDecision state Superceded version false</string>
        </history>
        <history>
          <datetime>2019-07-10T12:06:21Z</datetime>
          <agent>creator</agent>
          <event>modify</event>
          <order>19</order>
          <string>mod policy IMS_DCDecision state Superceded action '' input ''</string>
        </history>
        <history>
          <datetime>2019-07-10T12:06:21Z</datetime>
          <agent>creator</agent>
          <event>modify</event>
          <order>20</order>
          <string>mod policy IMS_DCDecision state Superceded check '' input ''</string>
        </history>
        <history>
          <datetime>2019-07-10T12:06:21Z</datetime>
          <agent>creator</agent>
          <event>modify</event>
          <order>21</order>
          <string>mod policy IMS_DCDecision state Superceded majorrevision true</string>
        </history>
        <history>
          <datetime>2019-07-10T12:06:21Z</datetime>
          <agent>creator</agent>
          <event>modify</event>
          <order>22</order>
          <string>mod policy IMS_DCDecision state Superceded minorrevision true</string>
        </history>
        <history>
          <datetime>2019-07-10T12:06:21Z</datetime>
          <agent>creator</agent>
          <event>modify</event>
          <order>23</order>
          <string>mod policy IMS_DCDecision state Superceded published false</string>
        </history>
        <history>
          <datetime>2019-07-10T12:06:21Z</datetime>
          <agent>creator</agent>
          <event>modify</event>
          <order>24</order>
          <string>mod policy IMS_DCDecision state Superceded owner create create,delete,read,revise,show,toconnect</string>
        </history>
        <history>
          <datetime>2019-07-10T12:06:21Z</datetime>
          <agent>creator</agent>
          <event>modify</event>
          <order>25</order>
          <string>mod policy IMS_DCDecision state Superceded public read read</string>
        </history>
        <history>
          <datetime>2019-07-10T12:06:21Z</datetime>
          <agent>creator</agent>
          <event>modify</event>
          <order>26</order>
          <string>mod policy IMS_DCDecision state Superceded public key ExtendedPublicReadAccess read read,show,toconnect,todisconnect ancestor organization public maturity filter expression[OrganizationPublicAccess]</string>
        </history>
        <history>
          <datetime>2019-07-10T12:06:21Z</datetime>
          <agent>creator</agent>
          <event>modify</event>
          <order>27</order>
          <string>mod policy IMS_DCDecision state Superceded user Employee read read,show,toconnect,todisconnect</string>
        </history>
        <history>
          <datetime>2019-07-10T12:06:21Z</datetime>
          <agent>creator</agent>
          <event>modify</event>
          <order>28</order>
          <string>mod policy IMS_DCDecision state Superceded user 'Exchange User' toconnect toconnect</string>
        </history>
        <history>
          <datetime>2019-07-10T12:06:21Z</datetime>
          <agent>creator</agent>
          <event>modify</event>
          <order>29</order>
          <string>mod policy IMS_DCDecision state Superceded user 'Global User' key owner delete delete,read,revise,show,toconnect single organization single project context owner</string>
        </history>
        <history>
          <datetime>2019-07-10T12:06:21Z</datetime>
          <agent>creator</agent>
          <event>modify</event>
          <order>30</order>
          <string>mod policy IMS_DCDecision state Superceded user Grant key grant_key all all single project</string>
        </history>
        <history>
          <datetime>2019-07-10T12:06:21Z</datetime>
          <agent>creator</agent>
          <event>modify</event>
          <order>31</order>
          <string>mod policy IMS_DCDecision state Superceded user VPLMLocalCrossOrgContextAccess key ExtendedContextualPrivateReadAccess checkout checkout,read,show,toconnect,todisconnect single project</string>
        </history>
        <history>
          <datetime>2019-07-10T12:06:21Z</datetime>
          <agent>creator</agent>
          <event>modify</event>
          <order>32</order>
          <string>mod policy IMS_DCDecision state Superceded user VPLMLocalCrossPrjContextAccess key ExtendedPublicReadAccess checkout checkout,read,show,toconnect,todisconnect ancestor organization notprivate maturity filter expression[OrganizationPublicAccess]</string>
        </history>
        <history>
          <datetime>2019-07-10T12:06:21Z</datetime>
          <agent>creator</agent>
          <event>modify</event>
          <order>33</order>
          <string>mod policy IMS_DCDecision state Superceded user VPLMSecuredCrossAccess key ExtendedReadAccessForPublicGuest checkout checkout,read,show,toconnect,todisconnect single organization single project notprivate maturity</string>
        </history>
        <history>
          <datetime>2019-07-10T12:06:21Z</datetime>
          <agent>creator</agent>
          <event>modify</event>
          <order>34</order>
          <string>mod policy IMS_DCDecision state Superceded login user VPLMAdmin key ExtendedCreateAccessForPLMAdmin delete delete,revise</string>
        </history>
        <history>
          <datetime>2019-07-10T12:06:21Z</datetime>
          <agent>creator</agent>
          <event>modify</event>
          <order>35</order>
          <string>mod policy IMS_DCDecision state Superceded login user VPLMExperimenter key ExtendedCreateAccessForPrivateAuthoring delete delete,revise single organization single project context owner</string>
        </history>
        <history>
          <datetime>2019-07-10T12:06:21Z</datetime>
          <agent>creator</agent>
          <event>modify</event>
          <order>36</order>
          <string>mod policy IMS_DCDecision state Superceded login user VPLMProjectLeader key ExtendedCreateAccessForTechnicalLeader delete delete,revise single organization single project</string>
        </history>
        <history>
          <datetime>2019-07-10T12:06:21Z</datetime>
          <agent>creator</agent>
          <event>modify</event>
          <order>37</order>
          <string>mod policy IMS_DCDecision state Active !enforcereserveaccess</string>
        </history>
        <history>
          <datetime>2019-07-10T12:06:21Z</datetime>
          <agent>creator</agent>
          <event>modify</event>
          <order>38</order>
          <string>mod policy IMS_DCDecision state Active promote true</string>
        </history>
        <history>
          <datetime>2019-07-10T12:06:21Z</datetime>
          <agent>creator</agent>
          <event>modify</event>
          <order>39</order>
          <string>mod policy IMS_DCDecision state Active checkoutHistory false</string>
        </history>
        <history>
          <datetime>2019-07-10T12:06:21Z</datetime>
          <agent>creator</agent>
          <event>modify</event>
          <order>40</order>
          <string>mod policy IMS_DCDecision state Active version false</string>
        </history>
        <history>
          <datetime>2019-07-10T12:06:21Z</datetime>
          <agent>creator</agent>
          <event>modify</event>
          <order>41</order>
          <string>mod policy IMS_DCDecision state Active action '' input ''</string>
        </history>
        <history>
          <datetime>2019-07-10T12:06:21Z</datetime>
          <agent>creator</agent>
          <event>modify</event>
          <order>42</order>
          <string>mod policy IMS_DCDecision state Active check '' input ''</string>
        </history>
        <history>
          <datetime>2019-07-10T12:06:21Z</datetime>
          <agent>creator</agent>
          <event>modify</event>
          <order>43</order>
          <string>mod policy IMS_DCDecision state Active majorrevision true</string>
        </history>
        <history>
          <datetime>2019-07-10T12:06:21Z</datetime>
          <agent>creator</agent>
          <event>modify</event>
          <order>44</order>
          <string>mod policy IMS_DCDecision state Active minorrevision true</string>
        </history>
        <history>
          <datetime>2019-07-10T12:06:21Z</datetime>
          <agent>creator</agent>
          <event>modify</event>
          <order>45</order>
          <string>mod policy IMS_DCDecision state Active published false</string>
        </history>
        <history>
          <datetime>2019-07-10T12:06:21Z</datetime>
          <agent>creator</agent>
          <event>modify</event>
          <order>46</order>
          <string>mod policy IMS_DCDecision state Active owner changename changename,changeowner,changepolicy,changetype,changevault,create,delete,disable,enable,fromconnect,fromdisconnect,grant,modify,promote,read,revoke,show,toconnect,todisconnect</string>
        </history>
        <history>
          <datetime>2019-07-10T12:06:21Z</datetime>
          <agent>creator</agent>
          <event>modify</event>
          <order>47</order>
          <string>mod policy IMS_DCDecision state Active public key ExtendedPublicReadAccess read read,show,toconnect,todisconnect ancestor organization public maturity filter expression[OrganizationPublicAccess]</string>
        </history>
        <history>
          <datetime>2019-07-10T12:06:21Z</datetime>
          <agent>creator</agent>
          <event>modify</event>
          <order>48</order>
          <string>mod policy IMS_DCDecision state Active user 'Access Grantor' checkin checkin,checkout,delete,fromconnect,fromdisconnect,grant,lock,modify,read,revise,revoke,show,toconnect,todisconnect,unlock</string>
        </history>
        <history>
          <datetime>2019-07-10T12:06:21Z</datetime>
          <agent>creator</agent>
          <event>modify</event>
          <order>49</order>
          <string>mod policy IMS_DCDecision state Active user Employee fromconnect fromconnect,fromdisconnect,read,show,toconnect,todisconnect</string>
        </history>
        <history>
          <datetime>2019-07-10T12:06:21Z</datetime>
          <agent>creator</agent>
          <event>modify</event>
          <order>50</order>
          <string>mod policy IMS_DCDecision state Active user 'Global User' key owner changename changename,changeowner,changepolicy,changetype,changevault,create,delete,disable,enable,fromconnect,fromdisconnect,grant,modify,promote,read,revoke,show,toconnect,todisconnect single organization single project context owner</string>
        </history>
        <history>
          <datetime>2019-07-10T12:06:21Z</datetime>
          <agent>creator</agent>
          <event>modify</event>
          <order>51</order>
          <string>mod policy IMS_DCDecision state Active user Grant key grant_key all all single project</string>
        </history>
        <history>
          <datetime>2019-07-10T12:06:21Z</datetime>
          <agent>creator</agent>
          <event>modify</event>
          <order>52</order>
          <string>mod policy IMS_DCDecision state Active user VPLMAdmin changename changename,changeowner,changepolicy,changetype,changevault,create,delete,fromconnect,fromdisconnect,modify,promote,read,revise,schedule,show,toconnect,todisconnect single organization single project</string>
        </history>
        <history>
          <datetime>2019-07-10T12:06:21Z</datetime>
          <agent>creator</agent>
          <event>modify</event>
          <order>53</order>
          <string>mod policy IMS_DCDecision state Active user VPLMCreator create create,delete,fromconnect,fromdisconnect,modify,read,revise,show,toconnect,todisconnect single organization single project</string>
        </history>
        <history>
          <datetime>2019-07-10T12:06:21Z</datetime>
          <agent>creator</agent>
          <event>modify</event>
          <order>54</order>
          <string>mod policy IMS_DCDecision state Active user VPLMLocalCrossOrgContextAccess key ExtendedContextualPrivateReadAccess checkout checkout,read,show,toconnect,todisconnect single project</string>
        </history>
        <history>
          <datetime>2019-07-10T12:06:21Z</datetime>
          <agent>creator</agent>
          <event>modify</event>
          <order>55</order>
          <string>mod policy IMS_DCDecision state Active user VPLMLocalCrossPrjContextAccess key ExtendedPublicReadAccess checkout checkout,read,show,toconnect,todisconnect ancestor organization public maturity filter expression[OrganizationPublicAccess]</string>
        </history>
        <history>
          <datetime>2019-07-10T12:06:21Z</datetime>
          <agent>creator</agent>
          <event>modify</event>
          <order>56</order>
          <string>mod policy IMS_DCDecision state Active user VPLMProjectLeader create create,delete,fromconnect,fromdisconnect,modify,read,revise,show,toconnect,todisconnect single organization single project</string>
        </history>
        <history>
          <datetime>2019-07-10T12:06:21Z</datetime>
          <agent>creator</agent>
          <event>modify</event>
          <order>57</order>
          <string>mod policy IMS_DCDecision state Active user VPLMSecuredCrossAccess key ExtendedReadAccessForPublicGuest checkout checkout,read,show,toconnect,todisconnect single organization single project public maturity</string>
        </history>
        <history>
          <datetime>2019-07-10T12:06:21Z</datetime>
          <agent>creator</agent>
          <event>modify</event>
          <order>58</order>
          <string>mod policy IMS_DCDecision state Active user VPLMViewer read read,show single organization single project</string>
        </history>
        <history>
          <datetime>2019-07-10T12:06:21Z</datetime>
          <agent>creator</agent>
          <event>modify</event>
          <order>59</order>
          <string>mod policy IMS_DCDecision state Active login owner key VPLMStrictOrgOwnershipIsFALSE demote demote,promote single project filter (!expression[VPLMStrictOrgOwnership])</string>
        </history>
        <history>
          <datetime>2019-07-10T12:06:21Z</datetime>
          <agent>creator</agent>
          <event>modify</event>
          <order>60</order>
          <string>mod policy IMS_DCDecision state Active login owner key VPLMStrictOrgOwnershipIsTRUE demote demote,promote single organization single project</string>
        </history>
        <history>
          <datetime>2019-07-10T12:06:21Z</datetime>
          <agent>creator</agent>
          <event>modify</event>
          <order>61</order>
          <string>mod policy IMS_DCDecision state Active login user VPLMAdmin key ExtendedCreateAccessForPLMAdmin create create,delete,revise</string>
        </history>
        <history>
          <datetime>2019-07-10T12:06:21Z</datetime>
          <agent>creator</agent>
          <event>modify</event>
          <order>62</order>
          <string>mod policy IMS_DCDecision state Active login user VPLMExperimenter key ExtendedCreateAccessForPrivateAuthoring create create,delete,revise single organization single project context owner</string>
        </history>
        <history>
          <datetime>2019-07-10T12:06:21Z</datetime>
          <agent>creator</agent>
          <event>modify</event>
          <order>63</order>
          <string><![CDATA[mod policy IMS_DCDecision state Active login user VPLMExperimenter key VPLMStrictOrgOwnershipIsFALSE1 changename changename,checkin,modify single project filter '(!expression[VPLMStrictOwnership_Evaluation]) && (!expression[VPLMStrictOrgOwnership])']]></string>
        </history>
        <history>
          <datetime>2019-07-10T12:06:21Z</datetime>
          <agent>creator</agent>
          <event>modify</event>
          <order>64</order>
          <string>mod policy IMS_DCDecision state Active login user VPLMExperimenter key VPLMStrictOrgOwnershipIsFALSE2 changename changename,checkin,modify single project context owner filter (!expression[VPLMStrictOrgOwnership])</string>
        </history>
        <history>
          <datetime>2019-07-10T12:06:21Z</datetime>
          <agent>creator</agent>
          <event>modify</event>
          <order>65</order>
          <string>mod policy IMS_DCDecision state Active login user VPLMExperimenter key VPLMStrictOrgOwnershipIsTRUE1 changename changename,checkin,modify single organization single project filter (!expression[VPLMStrictOwnership_Evaluation])</string>
        </history>
        <history>
          <datetime>2019-07-10T12:06:21Z</datetime>
          <agent>creator</agent>
          <event>modify</event>
          <order>66</order>
          <string>mod policy IMS_DCDecision state Active login user VPLMExperimenter key VPLMStrictOrgOwnershipIsTRUE2 changename changename,checkin,modify single organization single project context owner</string>
        </history>
        <history>
          <datetime>2019-07-10T12:06:21Z</datetime>
          <agent>creator</agent>
          <event>modify</event>
          <order>67</order>
          <string>mod policy IMS_DCDecision state Active login user VPLMProjectAdministrator key ExtendedModifyAccessForPrjAdmin changename changename,checkin,modify single project</string>
        </history>
        <history>
          <datetime>2019-07-10T12:06:21Z</datetime>
          <agent>creator</agent>
          <event>modify</event>
          <order>68</order>
          <string>mod policy IMS_DCDecision state Active login user VPLMProjectLeader key ExtendedCreateAccessForTechnicalLeader create create,delete,revise single organization single project</string>
        </history>
        <history>
          <datetime>2019-07-10T12:06:21Z</datetime>
          <agent>creator</agent>
          <event>modify</event>
          <order>69</order>
          <string>mod policy IMS_DCDecision state Active login user VPLMProjectLeader key VPLMStrictOrgOwnershipIsFALSE changename changename,checkin,demote,modify,promote single project filter (!expression[VPLMStrictOrgOwnership])</string>
        </history>
        <history>
          <datetime>2019-07-10T12:06:21Z</datetime>
          <agent>creator</agent>
          <event>modify</event>
          <order>70</order>
          <string>mod policy IMS_DCDecision state Active login user VPLMProjectLeader key VPLMStrictOrgOwnershipIsTRUE changename changename,checkin,demote,modify,promote single organization single project</string>
        </history>
        <history>
          <datetime>2019-07-10T12:06:21Z</datetime>
          <agent>creator</agent>
          <event>modify</event>
          <order>71</order>
          <string>mod policy IMS_DCDecision add property state_Superceded value Superceded</string>
        </history>
        <history>
          <datetime>2019-07-10T12:06:21Z</datetime>
          <agent>creator</agent>
          <event>modify</event>
          <order>72</order>
          <string>mod policy IMS_DCDecision add property state_Active value Active</string>
        </history>
        <history>
          <datetime>2019-07-10T12:06:21Z</datetime>
          <agent>creator</agent>
          <event>modify</event>
          <order>73</order>
          <string>mod policy IMS_DCDecision add property 'MxUpdate Sub Path'</string>
        </history>
        <history>
          <datetime>2019-07-10T12:06:21Z</datetime>
          <agent>creator</agent>
          <event>modify</event>
          <order>74</order>
          <string>mod policy IMS_DCDecision add property application value IMS_HNH</string>
        </history>
        <history>
          <datetime>2019-07-10T12:06:21Z</datetime>
          <agent>creator</agent>
          <event>modify</event>
          <order>75</order>
          <string>mod policy IMS_DCDecision add property 'file date' value '04-24-2019 14:19:54.000'</string>
        </history>
        <history>
          <datetime>2019-07-10T12:06:21Z</datetime>
          <agent>creator</agent>
          <event>modify</event>
          <order>76</order>
          <string>mod policy IMS_DCDecision add property 'installed date' value 07-10-2019</string>
        </history>
        <history>
          <datetime>2019-07-10T12:06:21Z</datetime>
          <agent>creator</agent>
          <event>modify</event>
          <order>77</order>
          <string>mod policy IMS_DCDecision add property installer value 'The MxUpdate Team'</string>
        </history>
        <history>
          <datetime>2019-07-10T12:06:21Z</datetime>
          <agent>creator</agent>
          <event>modify</event>
          <order>78</order>
          <string>mod policy IMS_DCDecision add property 'original name' value IMS_DCDecision</string>
        </history>
        <history>
          <datetime>2019-07-10T12:06:21Z</datetime>
          <agent>creator</agent>
          <event>modify</event>
          <order>79</order>
          <string>mod policy IMS_DCDecision add property state_Release value Release</string>
        </history>
        <history>
          <datetime>2019-07-10T12:06:21Z</datetime>
          <agent>creator</agent>
          <event>modify</event>
          <order>80</order>
          <string>mod policy IMS_DCDecision add property version value 1</string>
        </history>
      </historyList>
    </adminProperties>
    <sequence>1,2,3,...</sequence>
    <majorsequence></majorsequence>
    <delimiter></delimiter>
    <typeRefList count="1">
      <typeRef>IMS_DCDecision</typeRef>
    </typeRefList>
      <allstateDef>
        <name>allstate</name>
        <userAccessList count="8">
      <userAccess>
        <userAccessKind>public</userAccessKind>
        <matchOrganization>any</matchOrganization>
        <matchProject>any</matchProject>
        <matchOwner>any</matchOwner>
        <matchReserve>any</matchReserve>
        <matchMaturity>any</matchMaturity>
        <matchCategory>any</matchCategory>
        <access>
          <none/>
        </access>
      </userAccess>
      <userAccess>
        <userAccessKind>owner</userAccessKind>
        <matchOrganization>any</matchOrganization>
        <matchProject>any</matchProject>
        <matchOwner>any</matchOwner>
        <matchReserve>any</matchReserve>
        <matchMaturity>any</matchMaturity>
        <matchCategory>any</matchCategory>
        <access>
          <none/>
        </access>
      </userAccess>
      <userAccess>
        <userAccessKind>user</userAccessKind>
        <userRef>VPLMAdmin</userRef>
        <userAccessLoginRole></userAccessLoginRole>
        <userAccessKey>ExtendedModifyAccessForPLMAdmin</userAccessKey>
        <matchOrganization>any</matchOrganization>
        <matchProject>any</matchProject>
        <matchOwner>any</matchOwner>
        <matchReserve>any</matchReserve>
        <matchMaturity>any</matchMaturity>
        <matchCategory>any</matchCategory>
        <access>
          <modifyAccess/>
          <checkinAccess/>
          <changeNameAccess/>
        </access>
      </userAccess>
      <userAccess>
        <userAccessKind>user</userAccessKind>
        <userRef>VPLMAdmin</userRef>
        <userAccessLoginRole></userAccessLoginRole>
        <userAccessKey>ExtendedPromoteAccessForPLMAdmin</userAccessKey>
        <matchOrganization>any</matchOrganization>
        <matchProject>any</matchProject>
        <matchOwner>any</matchOwner>
        <matchReserve>any</matchReserve>
        <matchMaturity>any</matchMaturity>
        <matchCategory>any</matchCategory>
        <access>
          <promoteAccess/>
          <demoteAccess/>
        </access>
      </userAccess>
      <userAccess>
        <userAccessKind>user</userAccessKind>
        <userRef>VPLMAdmin</userRef>
        <userAccessLoginRole></userAccessLoginRole>
        <userAccessKey>ExtendedReadAccessForPLMAdmin</userAccessKey>
        <matchOrganization>any</matchOrganization>
        <matchProject>any</matchProject>
        <matchOwner>any</matchOwner>
        <matchReserve>any</matchReserve>
        <matchMaturity>any</matchMaturity>
        <matchCategory>any</matchCategory>
        <access>
          <readAccess/>
          <checkoutAccess/>
          <toConnectAccess/>
          <toDisconnectAccess/>
          <showAccess/>
        </access>
      </userAccess>
      <userAccess>
        <userAccessKind>user</userAccessKind>
        <userRef>IMS_AP_Designer</userRef>
        <matchOrganization>any</matchOrganization>
        <matchProject>any</matchProject>
        <matchOwner>any</matchOwner>
        <matchReserve>any</matchReserve>
        <matchMaturity>any</matchMaturity>
        <matchCategory>any</matchCategory>
        <access>
          <all/>
        </access>
      </userAccess>
      <userAccess>
        <userAccessKind>user</userAccessKind>
        <userRef>VPLMLocalCrossOrgContextAccess</userRef>
        <userAccessKey>ExtendedOwnerReadAccess</userAccessKey>
        <matchOrganization>any</matchOrganization>
        <matchProject>any</matchProject>
        <matchOwner>context</matchOwner>
        <matchReserve>any</matchReserve>
        <matchMaturity>any</matchMaturity>
        <matchCategory>any</matchCategory>
        <access>
          <readAccess/>
          <checkoutAccess/>
          <toConnectAccess/>
          <toDisconnectAccess/>
          <showAccess/>
        </access>
      </userAccess>
      <userAccess>
        <userAccessKind>user</userAccessKind>
        <userRef>Global User</userRef>
        <userAccessKey>SecuredGlobalUser</userAccessKey>
        <matchOrganization>ancestor</matchOrganization>
        <matchProject>ancestor</matchProject>
        <matchOwner>any</matchOwner>
        <matchReserve>any</matchReserve>
        <matchMaturity>any</matchMaturity>
        <matchCategory>any</matchCategory>
        <access>
          <readAccess/>
          <toConnectAccess/>
          <toDisconnectAccess/>
          <showAccess/>
        </access>
      </userAccess>
        </userAccessList>
      </allstateDef>
    <stateDefList count="2">
      <stateDef>
        <name>Active</name>
        <revisionable/>
        <majorrevisionable/>
        <autoPromotion/>
        <userAccessList count="26">
      <userAccess>
        <userAccessKind>public</userAccessKind>
        <matchOrganization>any</matchOrganization>
        <matchProject>any</matchProject>
        <matchOwner>any</matchOwner>
        <matchReserve>any</matchReserve>
        <matchMaturity>any</matchMaturity>
        <matchCategory>any</matchCategory>
        <access>
          <none/>
        </access>
      </userAccess>
      <userAccess>
        <userAccessKind>public</userAccessKind>
        <userAccessKey>ExtendedPublicReadAccess</userAccessKey>
        <matchOrganization>ancestor</matchOrganization>
        <matchProject>any</matchProject>
        <matchOwner>any</matchOwner>
        <matchReserve>any</matchReserve>
        <matchMaturity>public</matchMaturity>
        <matchCategory>any</matchCategory>
        <expressionFilter>expression[OrganizationPublicAccess]</expressionFilter>
        <access>
          <readAccess/>
          <toConnectAccess/>
          <toDisconnectAccess/>
          <showAccess/>
        </access>
      </userAccess>
      <userAccess>
        <userAccessKind>owner</userAccessKind>
        <userAccessLoginRole></userAccessLoginRole>
        <userAccessKey>VPLMStrictOrgOwnershipIsTRUE</userAccessKey>
        <matchOrganization>single</matchOrganization>
        <matchProject>single</matchProject>
        <matchOwner>any</matchOwner>
        <matchReserve>any</matchReserve>
        <matchMaturity>any</matchMaturity>
        <matchCategory>any</matchCategory>
        <access>
          <promoteAccess/>
          <demoteAccess/>
        </access>
      </userAccess>
      <userAccess>
        <userAccessKind>owner</userAccessKind>
        <userAccessLoginRole></userAccessLoginRole>
        <userAccessKey>VPLMStrictOrgOwnershipIsFALSE</userAccessKey>
        <matchOrganization>any</matchOrganization>
        <matchProject>single</matchProject>
        <matchOwner>any</matchOwner>
        <matchReserve>any</matchReserve>
        <matchMaturity>any</matchMaturity>
        <matchCategory>any</matchCategory>
        <expressionFilter>(!expression[VPLMStrictOrgOwnership])</expressionFilter>
        <access>
          <promoteAccess/>
          <demoteAccess/>
        </access>
      </userAccess>
      <userAccess>
        <userAccessKind>owner</userAccessKind>
        <matchOrganization>any</matchOrganization>
        <matchProject>any</matchProject>
        <matchOwner>any</matchOwner>
        <matchReserve>any</matchReserve>
        <matchMaturity>any</matchMaturity>
        <matchCategory>any</matchCategory>
        <access>
          <readAccess/>
          <modifyAccess/>
          <deleteAccess/>
          <changeOwnerAccess/>
          <createAccess/>
          <promoteAccess/>
          <enableAccess/>
          <disableAccess/>
          <changeVaultAccess/>
          <changeNameAccess/>
          <changePolicyAccess/>
          <changeTypeAccess/>
          <fromConnectAccess/>
          <toConnectAccess/>
          <fromDisconnectAccess/>
          <toDisconnectAccess/>
          <grantAccess/>
          <revokeAccess/>
          <showAccess/>
        </access>
      </userAccess>
      <userAccess>
        <userAccessKind>user</userAccessKind>
        <userRef>VPLMAdmin</userRef>
        <userAccessLoginRole></userAccessLoginRole>
        <userAccessKey>ExtendedCreateAccessForPLMAdmin</userAccessKey>
        <matchOrganization>any</matchOrganization>
        <matchProject>any</matchProject>
        <matchOwner>any</matchOwner>
        <matchReserve>any</matchReserve>
        <matchMaturity>any</matchMaturity>
        <matchCategory>any</matchCategory>
        <access>
          <deleteAccess/>
          <createAccess/>
          <reviseAccess/>
        </access>
      </userAccess>
      <userAccess>
        <userAccessKind>user</userAccessKind>
        <userRef>VPLMExperimenter</userRef>
        <userAccessLoginRole></userAccessLoginRole>
        <userAccessKey>ExtendedCreateAccessForPrivateAuthoring</userAccessKey>
        <matchOrganization>single</matchOrganization>
        <matchProject>single</matchProject>
        <matchOwner>context</matchOwner>
        <matchReserve>any</matchReserve>
        <matchMaturity>any</matchMaturity>
        <matchCategory>any</matchCategory>
        <access>
          <deleteAccess/>
          <createAccess/>
          <reviseAccess/>
        </access>
      </userAccess>
      <userAccess>
        <userAccessKind>user</userAccessKind>
        <userRef>VPLMProjectLeader</userRef>
        <userAccessLoginRole></userAccessLoginRole>
        <userAccessKey>ExtendedCreateAccessForTechnicalLeader</userAccessKey>
        <matchOrganization>single</matchOrganization>
        <matchProject>single</matchProject>
        <matchOwner>any</matchOwner>
        <matchReserve>any</matchReserve>
        <matchMaturity>any</matchMaturity>
        <matchCategory>any</matchCategory>
        <access>
          <deleteAccess/>
          <createAccess/>
          <reviseAccess/>
        </access>
      </userAccess>
      <userAccess>
        <userAccessKind>user</userAccessKind>
        <userRef>VPLMProjectAdministrator</userRef>
        <userAccessLoginRole></userAccessLoginRole>
        <userAccessKey>ExtendedModifyAccessForPrjAdmin</userAccessKey>
        <matchOrganization>any</matchOrganization>
        <matchProject>single</matchProject>
        <matchOwner>any</matchOwner>
        <matchReserve>any</matchReserve>
        <matchMaturity>any</matchMaturity>
        <matchCategory>any</matchCategory>
        <access>
          <modifyAccess/>
          <checkinAccess/>
          <changeNameAccess/>
        </access>
      </userAccess>
      <userAccess>
        <userAccessKind>user</userAccessKind>
        <userRef>VPLMProjectLeader</userRef>
        <userAccessLoginRole></userAccessLoginRole>
        <userAccessKey>VPLMStrictOrgOwnershipIsTRUE</userAccessKey>
        <matchOrganization>single</matchOrganization>
        <matchProject>single</matchProject>
        <matchOwner>any</matchOwner>
        <matchReserve>any</matchReserve>
        <matchMaturity>any</matchMaturity>
        <matchCategory>any</matchCategory>
        <access>
          <modifyAccess/>
          <checkinAccess/>
          <promoteAccess/>
          <demoteAccess/>
          <changeNameAccess/>
        </access>
      </userAccess>
      <userAccess>
        <userAccessKind>user</userAccessKind>
        <userRef>VPLMExperimenter</userRef>
        <userAccessLoginRole></userAccessLoginRole>
        <userAccessKey>VPLMStrictOrgOwnershipIsTRUE2</userAccessKey>
        <matchOrganization>single</matchOrganization>
        <matchProject>single</matchProject>
        <matchOwner>context</matchOwner>
        <matchReserve>any</matchReserve>
        <matchMaturity>any</matchMaturity>
        <matchCategory>any</matchCategory>
        <access>
          <modifyAccess/>
          <checkinAccess/>
          <changeNameAccess/>
        </access>
      </userAccess>
      <userAccess>
        <userAccessKind>user</userAccessKind>
        <userRef>VPLMProjectLeader</userRef>
        <userAccessLoginRole></userAccessLoginRole>
        <userAccessKey>VPLMStrictOrgOwnershipIsFALSE</userAccessKey>
        <matchOrganization>any</matchOrganization>
        <matchProject>single</matchProject>
        <matchOwner>any</matchOwner>
        <matchReserve>any</matchReserve>
        <matchMaturity>any</matchMaturity>
        <matchCategory>any</matchCategory>
        <expressionFilter>(!expression[VPLMStrictOrgOwnership])</expressionFilter>
        <access>
          <modifyAccess/>
          <checkinAccess/>
          <promoteAccess/>
          <demoteAccess/>
          <changeNameAccess/>
        </access>
      </userAccess>
      <userAccess>
        <userAccessKind>user</userAccessKind>
        <userRef>VPLMExperimenter</userRef>
        <userAccessLoginRole></userAccessLoginRole>
        <userAccessKey>VPLMStrictOrgOwnershipIsFALSE1</userAccessKey>
        <matchOrganization>any</matchOrganization>
        <matchProject>single</matchProject>
        <matchOwner>any</matchOwner>
        <matchReserve>any</matchReserve>
        <matchMaturity>any</matchMaturity>
        <matchCategory>any</matchCategory>
        <expressionFilter><![CDATA[(!expression[VPLMStrictOwnership_Evaluation]) && (!expression[VPLMStrictOrgOwnership])]]></expressionFilter>
        <access>
          <modifyAccess/>
          <checkinAccess/>
          <changeNameAccess/>
        </access>
      </userAccess>
      <userAccess>
        <userAccessKind>user</userAccessKind>
        <userRef>VPLMExperimenter</userRef>
        <userAccessLoginRole></userAccessLoginRole>
        <userAccessKey>VPLMStrictOrgOwnershipIsFALSE2</userAccessKey>
        <matchOrganization>any</matchOrganization>
        <matchProject>single</matchProject>
        <matchOwner>context</matchOwner>
        <matchReserve>any</matchReserve>
        <matchMaturity>any</matchMaturity>
        <matchCategory>any</matchCategory>
        <expressionFilter>(!expression[VPLMStrictOrgOwnership])</expressionFilter>
        <access>
          <modifyAccess/>
          <checkinAccess/>
          <changeNameAccess/>
        </access>
      </userAccess>
      <userAccess>
        <userAccessKind>user</userAccessKind>
        <userRef>VPLMExperimenter</userRef>
        <userAccessLoginRole></userAccessLoginRole>
        <userAccessKey>VPLMStrictOrgOwnershipIsTRUE1</userAccessKey>
        <matchOrganization>single</matchOrganization>
        <matchProject>single</matchProject>
        <matchOwner>any</matchOwner>
        <matchReserve>any</matchReserve>
        <matchMaturity>any</matchMaturity>
        <matchCategory>any</matchCategory>
        <expressionFilter>(!expression[VPLMStrictOwnership_Evaluation])</expressionFilter>
        <access>
          <modifyAccess/>
          <checkinAccess/>
          <changeNameAccess/>
        </access>
      </userAccess>
      <userAccess>
        <userAccessKind>user</userAccessKind>
        <userRef>VPLMAdmin</userRef>
        <matchOrganization>single</matchOrganization>
        <matchProject>single</matchProject>
        <matchOwner>any</matchOwner>
        <matchReserve>any</matchReserve>
        <matchMaturity>any</matchMaturity>
        <matchCategory>any</matchCategory>
        <access>
          <readAccess/>
          <modifyAccess/>
          <deleteAccess/>
          <changeOwnerAccess/>
          <createAccess/>
          <promoteAccess/>
          <scheduleAccess/>
          <reviseAccess/>
          <changeVaultAccess/>
          <changeNameAccess/>
          <changePolicyAccess/>
          <changeTypeAccess/>
          <fromConnectAccess/>
          <toConnectAccess/>
          <fromDisconnectAccess/>
          <toDisconnectAccess/>
          <showAccess/>
        </access>
      </userAccess>
      <userAccess>
        <userAccessKind>user</userAccessKind>
        <userRef>Employee</userRef>
        <matchOrganization>any</matchOrganization>
        <matchProject>any</matchProject>
        <matchOwner>any</matchOwner>
        <matchReserve>any</matchReserve>
        <matchMaturity>any</matchMaturity>
        <matchCategory>any</matchCategory>
        <access>
          <readAccess/>
          <fromConnectAccess/>
          <toConnectAccess/>
          <fromDisconnectAccess/>
          <toDisconnectAccess/>
          <showAccess/>
        </access>
      </userAccess>
      <userAccess>
        <userAccessKind>user</userAccessKind>
        <userRef>VPLMCreator</userRef>
        <matchOrganization>single</matchOrganization>
        <matchProject>single</matchProject>
        <matchOwner>any</matchOwner>
        <matchReserve>any</matchReserve>
        <matchMaturity>any</matchMaturity>
        <matchCategory>any</matchCategory>
        <access>
          <readAccess/>
          <modifyAccess/>
          <deleteAccess/>
          <createAccess/>
          <reviseAccess/>
          <fromConnectAccess/>
          <toConnectAccess/>
          <fromDisconnectAccess/>
          <toDisconnectAccess/>
          <showAccess/>
        </access>
      </userAccess>
      <userAccess>
        <userAccessKind>user</userAccessKind>
        <userRef>VPLMViewer</userRef>
        <matchOrganization>single</matchOrganization>
        <matchProject>single</matchProject>
        <matchOwner>any</matchOwner>
        <matchReserve>any</matchReserve>
        <matchMaturity>any</matchMaturity>
        <matchCategory>any</matchCategory>
        <access>
          <readAccess/>
          <showAccess/>
        </access>
      </userAccess>
      <userAccess>
        <userAccessKind>user</userAccessKind>
        <userRef>Access Grantor</userRef>
        <matchOrganization>any</matchOrganization>
        <matchProject>any</matchProject>
        <matchOwner>any</matchOwner>
        <matchReserve>any</matchReserve>
        <matchMaturity>any</matchMaturity>
        <matchCategory>any</matchCategory>
        <access>
          <readAccess/>
          <modifyAccess/>
          <deleteAccess/>
          <checkoutAccess/>
          <checkinAccess/>
          <lockAccess/>
          <unlockAccess/>
          <reviseAccess/>
          <fromConnectAccess/>
          <toConnectAccess/>
          <fromDisconnectAccess/>
          <toDisconnectAccess/>
          <grantAccess/>
          <revokeAccess/>
          <showAccess/>
        </access>
      </userAccess>
      <userAccess>
        <userAccessKind>user</userAccessKind>
        <userRef>VPLMProjectLeader</userRef>
        <matchOrganization>single</matchOrganization>
        <matchProject>single</matchProject>
        <matchOwner>any</matchOwner>
        <matchReserve>any</matchReserve>
        <matchMaturity>any</matchMaturity>
        <matchCategory>any</matchCategory>
        <access>
          <readAccess/>
          <modifyAccess/>
          <deleteAccess/>
          <createAccess/>
          <reviseAccess/>
          <fromConnectAccess/>
          <toConnectAccess/>
          <fromDisconnectAccess/>
          <toDisconnectAccess/>
          <showAccess/>
        </access>
      </userAccess>
      <userAccess>
        <userAccessKind>user</userAccessKind>
        <userRef>VPLMLocalCrossOrgContextAccess</userRef>
        <userAccessKey>ExtendedContextualPrivateReadAccess</userAccessKey>
        <matchOrganization>any</matchOrganization>
        <matchProject>single</matchProject>
        <matchOwner>any</matchOwner>
        <matchReserve>any</matchReserve>
        <matchMaturity>any</matchMaturity>
        <matchCategory>any</matchCategory>
        <access>
          <readAccess/>
          <checkoutAccess/>
          <toConnectAccess/>
          <toDisconnectAccess/>
          <showAccess/>
        </access>
      </userAccess>
      <userAccess>
        <userAccessKind>user</userAccessKind>
        <userRef>VPLMSecuredCrossAccess</userRef>
        <userAccessKey>ExtendedReadAccessForPublicGuest</userAccessKey>
        <matchOrganization>single</matchOrganization>
        <matchProject>single</matchProject>
        <matchOwner>any</matchOwner>
        <matchReserve>any</matchReserve>
        <matchMaturity>public</matchMaturity>
        <matchCategory>any</matchCategory>
        <access>
          <readAccess/>
          <checkoutAccess/>
          <toConnectAccess/>
          <toDisconnectAccess/>
          <showAccess/>
        </access>
      </userAccess>
      <userAccess>
        <userAccessKind>user</userAccessKind>
        <userRef>Grant</userRef>
        <userAccessKey>grant_key</userAccessKey>
        <matchOrganization>any</matchOrganization>
        <matchProject>single</matchProject>
        <matchOwner>any</matchOwner>
        <matchReserve>any</matchReserve>
        <matchMaturity>any</matchMaturity>
        <matchCategory>any</matchCategory>
        <access>
          <all/>
        </access>
      </userAccess>
      <userAccess>
        <userAccessKind>user</userAccessKind>
        <userRef>Global User</userRef>
        <userAccessKey>owner</userAccessKey>
        <matchOrganization>single</matchOrganization>
        <matchProject>single</matchProject>
        <matchOwner>context</matchOwner>
        <matchReserve>any</matchReserve>
        <matchMaturity>any</matchMaturity>
        <matchCategory>any</matchCategory>
        <access>
          <readAccess/>
          <modifyAccess/>
          <deleteAccess/>
          <changeOwnerAccess/>
          <createAccess/>
          <promoteAccess/>
          <enableAccess/>
          <disableAccess/>
          <changeVaultAccess/>
          <changeNameAccess/>
          <changePolicyAccess/>
          <changeTypeAccess/>
          <fromConnectAccess/>
          <toConnectAccess/>
          <fromDisconnectAccess/>
          <toDisconnectAccess/>
          <grantAccess/>
          <revokeAccess/>
          <showAccess/>
        </access>
      </userAccess>
      <userAccess>
        <userAccessKind>user</userAccessKind>
        <userRef>VPLMLocalCrossPrjContextAccess</userRef>
        <userAccessKey>ExtendedPublicReadAccess</userAccessKey>
        <matchOrganization>ancestor</matchOrganization>
        <matchProject>any</matchProject>
        <matchOwner>any</matchOwner>
        <matchReserve>any</matchReserve>
        <matchMaturity>public</matchMaturity>
        <matchCategory>any</matchCategory>
        <expressionFilter>expression[OrganizationPublicAccess]</expressionFilter>
        <access>
          <readAccess/>
          <checkoutAccess/>
          <toConnectAccess/>
          <toDisconnectAccess/>
          <showAccess/>
        </access>
      </userAccess>
        </userAccessList>
      </stateDef>
      <stateDef>
        <name>Superceded</name>
        <revisionable/>
        <majorrevisionable/>
        <userAccessList count="13">
      <userAccess>
        <userAccessKind>public</userAccessKind>
        <matchOrganization>any</matchOrganization>
        <matchProject>any</matchProject>
        <matchOwner>any</matchOwner>
        <matchReserve>any</matchReserve>
        <matchMaturity>any</matchMaturity>
        <matchCategory>any</matchCategory>
        <access>
          <readAccess/>
        </access>
      </userAccess>
      <userAccess>
        <userAccessKind>public</userAccessKind>
        <userAccessKey>ExtendedPublicReadAccess</userAccessKey>
        <matchOrganization>ancestor</matchOrganization>
        <matchProject>any</matchProject>
        <matchOwner>any</matchOwner>
        <matchReserve>any</matchReserve>
        <matchMaturity>public</matchMaturity>
        <matchCategory>any</matchCategory>
        <expressionFilter>expression[OrganizationPublicAccess]</expressionFilter>
        <access>
          <readAccess/>
          <toConnectAccess/>
          <toDisconnectAccess/>
          <showAccess/>
        </access>
      </userAccess>
      <userAccess>
        <userAccessKind>owner</userAccessKind>
        <matchOrganization>any</matchOrganization>
        <matchProject>any</matchProject>
        <matchOwner>any</matchOwner>
        <matchReserve>any</matchReserve>
        <matchMaturity>any</matchMaturity>
        <matchCategory>any</matchCategory>
        <access>
          <readAccess/>
          <deleteAccess/>
          <createAccess/>
          <reviseAccess/>
          <toConnectAccess/>
          <showAccess/>
        </access>
      </userAccess>
      <userAccess>
        <userAccessKind>user</userAccessKind>
        <userRef>VPLMAdmin</userRef>
        <userAccessLoginRole></userAccessLoginRole>
        <userAccessKey>ExtendedCreateAccessForPLMAdmin</userAccessKey>
        <matchOrganization>any</matchOrganization>
        <matchProject>any</matchProject>
        <matchOwner>any</matchOwner>
        <matchReserve>any</matchReserve>
        <matchMaturity>any</matchMaturity>
        <matchCategory>any</matchCategory>
        <access>
          <deleteAccess/>
          <reviseAccess/>
        </access>
      </userAccess>
      <userAccess>
        <userAccessKind>user</userAccessKind>
        <userRef>VPLMExperimenter</userRef>
        <userAccessLoginRole></userAccessLoginRole>
        <userAccessKey>ExtendedCreateAccessForPrivateAuthoring</userAccessKey>
        <matchOrganization>single</matchOrganization>
        <matchProject>single</matchProject>
        <matchOwner>context</matchOwner>
        <matchReserve>any</matchReserve>
        <matchMaturity>any</matchMaturity>
        <matchCategory>any</matchCategory>
        <access>
          <deleteAccess/>
          <reviseAccess/>
        </access>
      </userAccess>
      <userAccess>
        <userAccessKind>user</userAccessKind>
        <userRef>VPLMProjectLeader</userRef>
        <userAccessLoginRole></userAccessLoginRole>
        <userAccessKey>ExtendedCreateAccessForTechnicalLeader</userAccessKey>
        <matchOrganization>single</matchOrganization>
        <matchProject>single</matchProject>
        <matchOwner>any</matchOwner>
        <matchReserve>any</matchReserve>
        <matchMaturity>any</matchMaturity>
        <matchCategory>any</matchCategory>
        <access>
          <deleteAccess/>
          <reviseAccess/>
        </access>
      </userAccess>
      <userAccess>
        <userAccessKind>user</userAccessKind>
        <userRef>Employee</userRef>
        <matchOrganization>any</matchOrganization>
        <matchProject>any</matchProject>
        <matchOwner>any</matchOwner>
        <matchReserve>any</matchReserve>
        <matchMaturity>any</matchMaturity>
        <matchCategory>any</matchCategory>
        <access>
          <readAccess/>
          <toConnectAccess/>
          <toDisconnectAccess/>
          <showAccess/>
        </access>
      </userAccess>
      <userAccess>
        <userAccessKind>user</userAccessKind>
        <userRef>Exchange User</userRef>
        <matchOrganization>any</matchOrganization>
        <matchProject>any</matchProject>
        <matchOwner>any</matchOwner>
        <matchReserve>any</matchReserve>
        <matchMaturity>any</matchMaturity>
        <matchCategory>any</matchCategory>
        <access>
          <toConnectAccess/>
        </access>
      </userAccess>
      <userAccess>
        <userAccessKind>user</userAccessKind>
        <userRef>VPLMLocalCrossOrgContextAccess</userRef>
        <userAccessKey>ExtendedContextualPrivateReadAccess</userAccessKey>
        <matchOrganization>any</matchOrganization>
        <matchProject>single</matchProject>
        <matchOwner>any</matchOwner>
        <matchReserve>any</matchReserve>
        <matchMaturity>any</matchMaturity>
        <matchCategory>any</matchCategory>
        <access>
          <readAccess/>
          <checkoutAccess/>
          <toConnectAccess/>
          <toDisconnectAccess/>
          <showAccess/>
        </access>
      </userAccess>
      <userAccess>
        <userAccessKind>user</userAccessKind>
        <userRef>VPLMSecuredCrossAccess</userRef>
        <userAccessKey>ExtendedReadAccessForPublicGuest</userAccessKey>
        <matchOrganization>single</matchOrganization>
        <matchProject>single</matchProject>
        <matchOwner>any</matchOwner>
        <matchReserve>any</matchReserve>
        <matchMaturity>notprivate</matchMaturity>
        <matchCategory>any</matchCategory>
        <access>
          <readAccess/>
          <checkoutAccess/>
          <toConnectAccess/>
          <toDisconnectAccess/>
          <showAccess/>
        </access>
      </userAccess>
      <userAccess>
        <userAccessKind>user</userAccessKind>
        <userRef>Grant</userRef>
        <userAccessKey>grant_key</userAccessKey>
        <matchOrganization>any</matchOrganization>
        <matchProject>single</matchProject>
        <matchOwner>any</matchOwner>
        <matchReserve>any</matchReserve>
        <matchMaturity>any</matchMaturity>
        <matchCategory>any</matchCategory>
        <access>
          <all/>
        </access>
      </userAccess>
      <userAccess>
        <userAccessKind>user</userAccessKind>
        <userRef>Global User</userRef>
        <userAccessKey>owner</userAccessKey>
        <matchOrganization>single</matchOrganization>
        <matchProject>single</matchProject>
        <matchOwner>context</matchOwner>
        <matchReserve>any</matchReserve>
        <matchMaturity>any</matchMaturity>
        <matchCategory>any</matchCategory>
        <access>
          <readAccess/>
          <deleteAccess/>
          <reviseAccess/>
          <toConnectAccess/>
          <showAccess/>
        </access>
      </userAccess>
      <userAccess>
        <userAccessKind>user</userAccessKind>
        <userRef>VPLMLocalCrossPrjContextAccess</userRef>
        <userAccessKey>ExtendedPublicReadAccess</userAccessKey>
        <matchOrganization>ancestor</matchOrganization>
        <matchProject>any</matchProject>
        <matchOwner>any</matchOwner>
        <matchReserve>any</matchReserve>
        <matchMaturity>notprivate</matchMaturity>
        <matchCategory>any</matchCategory>
        <expressionFilter>expression[OrganizationPublicAccess]</expressionFilter>
        <access>
          <readAccess/>
          <checkoutAccess/>
          <toConnectAccess/>
          <toDisconnectAccess/>
          <showAccess/>
        </access>
      </userAccess>
        </userAccessList>
      </stateDef>
    </stateDefList>
  </policy>
</ematrix>
